LICENSE.md
MANIFEST.in
README.md
pyproject.toml
setup.cfg
setup.py
libttp/__init__.py
libttp/ttp.py
libttp/ttpCython.c
libttp/ttpCython.pyx
libttp.egg-info/PKG-INFO
libttp.egg-info/SOURCES.txt
libttp.egg-info/dependency_links.txt
libttp.egg-info/requires.txt
libttp.egg-info/top_level.txt