Metadata-Version: 2.1
Name: libttp
Version: 0.1.42
Summary: Libraries for reading the data from time-tagging module (BrightEyes-TTM, https://github.com/VicidominiLab/BrightEyes-TTM)
Home-page: https://github.com/VicidominiLab/libttp
Author: Mattia Donato
Author-email: mattia.donato@iit.it
License: CC-BY-NC-4.0
License-File: LICENSE.md
Requires-Dist: cython>=0.29.30
Requires-Dist: numpy>=1.22.0
Requires-Dist: matplotlib
Requires-Dist: pandas
Requires-Dist: tdqm
Requires-Dist: scipy
